Metadata-Version: 1.1
Name: prometheus-writer
Version: 0.1.2
Summary: prometheus remote writer.
Home-page: https://github.com/liaozhaoyan/prometheus-writer
Author: liaozhaoyan
Author-email: zhaoyan.liao@linux.alibaba.com
License: Apache
Keywords: prometheus remote writer
Platform: UNKNOWN
Classifier: Topic :: System :: Operating System Kernels :: Linux
Classifier: Programming Language :: Python
Classifier: Programming Language :: Python :: 2
Classifier: Programming Language :: Python :: 2.7
Classifier: Programming Language :: Python :: 3
Classifier: Programming Language :: Python :: 3.5
Classifier: Programming Language :: Python :: 3.6
Classifier: Programming Language :: Python :: 3.7
Classifier: Programming Language :: Python :: 3.8
Classifier: Programming Language :: Python :: 3.9
Classifier: Programming Language :: Python :: 3.10
Classifier: Programming Language :: Python :: Implementation :: PyPy
